decision_rules/__init__.py
decision_rules/conditions.py
decision_rules/histogram.py
decision_rules/measures.py
decision_rules/problem.py
decision_rules/settings.py
decision_rules/classification/__init__.py
decision_rules/classification/metrics.py
decision_rules/classification/prediction.py
decision_rules/classification/prediction_indicators.py
decision_rules/classification/rule.py
decision_rules/classification/ruleset.py
decision_rules/core/__init__.py
decision_rules/core/condition.py
decision_rules/core/coverage.py
decision_rules/core/exceptions.py
decision_rules/core/metrics.py
decision_rules/core/prediction.py
decision_rules/core/rule.py
decision_rules/core/ruleset.py
decision_rules/core/simplifier.py
decision_rules/core/test_measures.py
decision_rules/filtering/__init__.py
decision_rules/filtering/_backward.py
decision_rules/filtering/_coverage.py
decision_rules/filtering/_forward.py
decision_rules/filtering/_helpers.py
decision_rules/filtering/_main.py
decision_rules/helpers/__init__.py
decision_rules/helpers/dataset_transformer.py
decision_rules/helpers/measures.py
decision_rules/helpers/p_values.py
decision_rules/importances/__init__.py
decision_rules/importances/_classification/__init__.py
decision_rules/importances/_classification/attributes.py
decision_rules/importances/_classification/conditions.py
decision_rules/importances/_core/__init__.py
decision_rules/importances/_core/attributes.py
decision_rules/importances/_core/conditions.py
decision_rules/importances/_regression/__init__.py
decision_rules/importances/_regression/attributes.py
decision_rules/importances/_regression/conditions.py
decision_rules/importances/_survival/__init__.py
decision_rules/importances/_survival/attributes.py
decision_rules/importances/_survival/conditions.py
decision_rules/regression/__init__.py
decision_rules/regression/metrics.py
decision_rules/regression/prediction.py
decision_rules/regression/prediction_indicators.py
decision_rules/regression/rule.py
decision_rules-1.4.1.dist-info/LICENSE
decision_rules-1.4.1.dist-info/METADATA
decision_rules-1.4.1.dist-info/WHEEL
decision_rules-1.4.1.dist-info/top_level.txt
decision_rules-1.4.1.dist-info/RECORD
