Metadata-Version: 2.1
Name: decision_rules
Version: 1.4.1
Summary: Package implementing decision rules. Includes tools for calculations of various measures and indicators, as well as algorithms for filtering rulesets.
Author: Cezary Maszczyk, Dawid Macha, Adam Grzelak, Bartosz Piguła
Author-email: cezary.maszczyk@emag.lukasiewicz.gov.pl
Requires-Python: >=3.9
License-File: LICENSE
Requires-Dist: numpy>=1.24
Requires-Dist: pandas>=1.5
Requires-Dist: pydantic>=2.0
Requires-Dist: scipy>=1.11
Requires-Dist: scikit-learn>=1.1
Requires-Dist: imbalanced-learn>=0.10
Requires-Dist: typeguard>=4.3
Requires-Dist: packaging>=14.1
